.coveragerc
.editorconfig
.eslintignore
.eslintrc.js
.gitignore
.gitlab-ci.yml
.htmllintrc
.stylelintrc.js
.travis.yml
LICENSE
MANIFEST.in
README.rst
requirements.txt
setup.cfg
setup.py
doc/images/nlg-ide-input.png
doc/images/nlg-ide-toplist.gif
doc/images/nlg-template-settings.png
examples/intro-narrative-api.ipynb
nlg/__init__.py
nlg/grammar.py
nlg/narrative.py
nlg/search.py
nlg/utils.py
nlg/webapp.py
nlg.egg-info/PKG-INFO
nlg.egg-info/SOURCES.txt
nlg.egg-info/dependency_links.txt
nlg.egg-info/requires.txt
nlg.egg-info/top_level.txt
nlg/app/__init__.py
nlg/app/body.html
nlg/app/gramex.yaml
nlg/app/index.html
nlg/app/login.html
nlg/app/nlg.js
nlg/app/setup.sh
nlg/app/style.css
nlg/app/template-navbar.html
nlg/app/__pycache__/__init__.cpython-37.pyc
nlg/app/error/400.html
nlg/app/error/401.html
nlg/app/error/403.html
nlg/app/error/404.html
nlg/app/error/500.html
nlg/app/html/demo.html
nlg/app/html/template-navbar.html
nlg/app/templates/demo.tmpl
nlg/app/templates/new-variable.tmpl
nlg/app/templates/template-settings.tmpl
nlg/app/templates/variable-settings.tmpl
nlg/tests/__init__.py
nlg/tests/test_grammar.py
nlg/tests/test_narrative.py
nlg/tests/test_search.py
nlg/tests/test_utils.py
nlg/tests/test_webapp.py
nlg/tests/data/actors.csv
nlg/tests/data/imdb_ratings.csv