Metadata-Version: 2.1
Name: nlg
Version: 0.1.3
Summary: Natural Language Generation framework for Python.
Home-page: https://github.com/gramener/gramex-nlg
Download-URL: https://pypi.org/project/nlg/#files
Maintainer: Jaidev Deshpande
Maintainer-email: jaidev.deshpande@gramener.com
License: MIT
Platform: UNKNOWN
License-File: LICENSE
